LICENSE
MANIFEST.in
README.rst
setup.py
comments/__init__.py
comments/admin.py
comments/apps.py
comments/models.py
comments/tests.py
comments/views.py
comments/api/__init__.py
comments/api/permissions.py
comments/api/serializers.py
comments/api/urls.py
comments/api/views.py
comments/migrations/0001_initial.py
comments/migrations/__init__.py
comments/static/comments/css/cfe.comments.css
comments/static/comments/img/user.png
comments/static/comments/js/srvup.comments.js
comments/static/comments/js/srvup.safeajax.js
comments/templates/comments/comments-loader.html
comments/templatetags/__init__.py
comments/templatetags/load_comments.py
docs/blank.txt
srvup_comments.egg-info/PKG-INFO
srvup_comments.egg-info/SOURCES.txt
srvup_comments.egg-info/dependency_links.txt
srvup_comments.egg-info/top_level.txt